bsphud/__init__.py
bsphud/__main__.py
bsphud/bsphud.py
bsphud-1.0.5.dist-info/LICENSE.txt
bsphud-1.0.5.dist-info/METADATA
bsphud-1.0.5.dist-info/WHEEL
bsphud-1.0.5.dist-info/entry_points.txt
bsphud-1.0.5.dist-info/top_level.txt
bsphud-1.0.5.dist-info/RECORD
