Metadata-Version: 2.2
Name: bsphud
Version: 1.0.5
Summary: Desktop switcher popup for BSPWM
Author-email: maybetree <maybetree48@proton.me>
License: Apache License
Classifier: Programming Language :: Python :: 3
Requires-Python: >=3
License-File: LICENSE.txt
